ai_agent_toolbox/__init__.py
ai_agent_toolbox/parser.py
ai_agent_toolbox/parser_event.py
ai_agent_toolbox/parser_utils.py
ai_agent_toolbox/prompt_formatter.py
ai_agent_toolbox/py.typed
ai_agent_toolbox/tool_parser.py
ai_agent_toolbox/tool_parser_state.py
ai_agent_toolbox/tool_response.py
ai_agent_toolbox/tool_use.py
ai_agent_toolbox/toolbox.py
ai_agent_toolbox/xml_parser.py
ai_agent_toolbox/xml_prompt_formatter.py
ai_agent_toolbox-1.0.3.dist-info/licenses/LICENSE
ai_agent_toolbox-1.0.3.dist-info/METADATA
ai_agent_toolbox-1.0.3.dist-info/WHEEL
ai_agent_toolbox-1.0.3.dist-info/top_level.txt
ai_agent_toolbox-1.0.3.dist-info/RECORD
