Metadata-Version: 2.4
Name: ai-agent-toolbox
Version: 1.0.3
Summary: An easy to use framework for adding tool use to AI agents.
Author-email: "255labs.xyz" <martyn@255bits.com>
License-Expression: MIT
Project-URL: Homepage, https://github.com/255BITS/ai-agent-toolbox
Classifier: Programming Language :: Python :: 3
Classifier: Operating System :: OS Independent
Requires-Python: >=3.7
License-File: LICENSE
Provides-Extra: dev
Requires-Dist: pytest; extra == "dev"
Dynamic: license-file
